Metadata-Version: 2.1
Name: dfcompy
Version: 1.0.0
Summary: A tool for comparing two Pandas DataFrame objects
Author: GuangJun Liang
Author-email: gaungjun_l@icloud.com
Keywords: python,pandas,dataframe,compare,diff,data analysis
Classifier: Development Status :: 3 - Alpha
Classifier: Intended Audience :: Developers
Classifier: Programming Language :: Python :: 3
Classifier: Operating System :: Unix
Classifier: Operating System :: MacOS :: MacOS X
Classifier: Operating System :: Microsoft :: Windows
Classifier: License :: OSI Approved :: MIT License
License-File: LICENSE.txt
Requires-Dist: pandas
Requires-Dist: tabulate
